Workbook

Sheet LEEME
B2: ACTIVIDAD 4 — CONJUNTOS DE DATOS
C3: Comparación de modelos preentrenados de Hugging Face para la lectura de notas de mercado
B5: Alumno | C5: Eduardo Aburto Angulo · Banquero Patrimonial Sr., BBVA México · plaza Xalapa
B6: Matrícula | C6: AL07182743
B7: Docente | C7: M. en C. Luis Ariel Vázquez Piña · Universidad Tecmilenio
B8: Fecha | C8: 9 de octubre de 2026
B10: QUÉ CONTIENE ESTE LIBRO
B12: NOTAS_MERCADO | C12: SINTÉTICO, DECLARADO. 400 notas de mercado en español etiquetadas por impacto (POSITIVO / NEUTRAL / NEGATIVO). Es el conjunto con el que se comparan los cuatro modelos.
B13: CATALOGO_FONDOS | C13: REAL. 484 series de 59 fondos, tomadas del Anaquel con Rendimientos Históricos de BBVA México del 08/10/2026, documento público. Ninguna cifra fue estimada.
B14: CLIENTES | C14: SINTÉTICO, DECLARADO. 150 clientes con posiciones de 5 a 20 millones de pesos, que es el tamaño de cartera de un banquero patrimonial senior.
B15: DICCIONARIO | C15: Descripción campo por campo de los tres conjuntos.
B16: RESUMEN | C16: Conteos y distribuciones, calculados con fórmulas sobre las hojas de datos.
B18: POR QUÉ HAY DATOS SIMULADOS
C19: Las notas de análisis de la mesa son material propietario y no puedo publicarlas en un repositorio académico. Las carteras de clientes son datos personales y financieros protegidos por la LFPDPPP.
C20: Para fines didácticos y por privacidad de los datos usamos nombres de superhéroes y villanos, ya que les puedo simular características individuales relacionadas con la ficción para poder comprobar la lógica de los resultados.
C21: Lo que sí es real son los fondos, sus categorías y sus rendimientos, tomados del anaquel que BBVA publica todos los días.
B23: REPRODUCIBILIDAD
C24: Los generadores son deterministas con la semilla 20261008. Dos comandos reproducen todo:
C25: python3 src/parse_anaquel.py anaquel.txt data/catalogo_fondos.csv
C26: python3 src/build_dataset.py

Sheet NOTAS_MERCADO
A1: id | B1: fecha | C1: fuente | D1: clase_activo | E1: texto | F1: impacto | G1: fenomeno | H1: dificultad | I1: fondos_relacionados
A2: N0001 | B2: 2026-10-05 | C2: Prensa financiera | D2: Deuda Largo Plazo | E2: El rendimiento del bono a treinta años subió 10 puntos base y generó minusvalías en los fondos de larga duración. | F2: NEGATIVO | G2: directo | H2: facil | I2: BBVACOR, BBVADGA
A3: N0002 | B3: 2026-10-05 | C3: Resumen de mesa | D3: Renta Variable Nacional | E3: Flash informativo: El índice de referencia de la bolsa mexicana avanzó 5.5 por ciento impulsado por el sector consumo. Se recomienda revisar la exposición de las carteras afectadas. | F3: POSITIVO | G3: directo | H3: facil | I3: BBVARFG, BBVARV
A4: N0003 | B4: 2026-10-08 | C4: Nota de análisis | D4: Deuda Corto Plazo | E4: Nota de la mesa de análisis: La inflación subyacente no sorprendió al alza y se mantuvo dentro del rango objetivo. El equipo de inversiones dará seguimiento en la sesión del lunes. | F4: POSITIVO | G4: negacion | H4: dificil | I4: BBVAGOB, BBVAUDI
A5: N0004 | B5: 2026-10-02 | C5: Comunicado oficial | D5: Deuda Corto Plazo | E5: Banxico recortó la tasa de referencia en 25 puntos base; las tasas de fondeo a un día siguen en niveles atractivos para los fondos de liquidez. Se recomienda revisar la exposición de las carteras afectadas. | F5: POSITIVO | G5: directo | H5: facil | I5: BBVARF, BBVALIQ
A6: N0005 | B6: 2026-10-03 | C6: Nota de análisis | D6: Deuda Corto Plazo | E6: A pesar del buen dato de empleo, el componente de servicios de la inflación volvió a presionar las tasas de corto plazo. | F6: NEGATIVO | G6: contraste | H6: dificil | I6: BBVADD, BBVAGB2
A7: N0006 | B7: 2026-10-02 | C7: Nota de análisis | D7: Deuda Largo Plazo | E7: El fondo cerró el mes con minusvalía de 1.6 por ciento, pero el devengo acumulado del año sigue en terreno positivo y la duración juega a favor. La información se actualizará con el cierre oficial. | F7: POSITIVO | G7: cifra_mixta | H7: media | I7: BBVAGLP, BBVACOR
A8: N0007 | B8: 2026-10-07 | C8: Nota de análisis | D8: Renta Variable Nacional | E8: La emisora reportó utilidades por arriba del consenso y elevó su guía para el cierre del año. | F8: POSITIVO | G8: directo | H8: facil | I8: BBVARV, BBVARFL
A9: N0008 | B9: 2026-10-08 | C9: Comunicado oficial | D9: Deuda Largo Plazo | E9: Resumen diario de mercados: La calificadora puso en perspectiva negativa la deuda corporativa del sector y advirtió sobre el nivel de apalancamiento. | F9: NEGATIVO | G9: directo | H9: facil | I9: BBVADGA, BBVAUDI
A10: N0009 | B10: 2026-10-01 | C10: Resumen de mesa | D10: Deuda Largo Plazo | E10: El fondo cerró el mes con minusvalía de 1.1 por ciento, pero el devengo acumulado del año sigue en terreno positivo y la duración juega a favor. La información se actualizará con el cierre oficial. | F10: POSITIVO | G10: cifra_mixta | H10: media | I10: BBVACOR, BBVADLP
A11: N0010 | B11: 2026-10-05 | C11: Nota de análisis | D11: Deuda Largo Plazo | E11: Resumen diario de mercados: Si bien el entorno global sigue incierto, los udibonos capturaron la compresión de spreads de la semana. | F11: POSITIVO | G11: contraste | H11: dificil | I11: BBVAMRF, BBVADLP
A12: N0011 | B12: 2026-10-01 | C12: Resumen de mesa | D12: Renta Variable Internacional | E12: Aunque la inflación estadounidense cedió, el mercado accionario cayó por el temor a una desaceleración más profunda. | F12: NEGATIVO | G12: contraste | H12: dificil | I12: BBVAEMG, BBVACAP
... A401: N0400 | B401: 2026-10-03 | C401: Nota de análisis | D401: Renta Variable Internacional | E401: Cierre de mercado: Aunque la inflación estadounidense cedió, el mercado accionario cayó por el temor a una desaceleración más profunda. La información se actualizará con el cierre oficial. | F401: NEGATIVO | G401: contraste | H401: dificil | I401: BBVARFG, BBVADIG

Sheet CATALOGO_FONDOS
A1: fondo | B1: serie | C1: publico | D1: familia | E1: categoria | F1: calificacion | G1: minimo_inversion | H1: rend_diario | I1: rend_semanal | J1: rend_acum_mes | K1: rend_acum_anio | L1: rend_1_anio | M1: rend_2_anios | N1: precio
A2: B+EDUCA | B2: B | C2: Personas Físicas | D2: Fondos de Deuda | E2: Deuda Corto Plazo | F2: AAA/1 | G2: 5000 | H2: 5.23 | I2: 5.23 | J2: 5.23 | K2: 5.39 | L2: 5.67 | M2: 7.06 | N2: 0.254413
A3: BBVAGB2 | B3: B1 | C3: Personas Físicas | D3: Fondos de Deuda | E3: Deuda Corto Plazo | F3: AAA/2 | G3: 0 | H3: 4.39 | I3: 5.47 | J3: 5.47 | K3: 3.99 | L3: 4.24 | M3: 5.72 | N3: 35.322377
A4: BBVAGUB | B4: C | C4: Personas Físicas | D4: Fondos de Deuda | E4: Deuda Corto Plazo | F4: AAA/1 | G4: 0 | H4: 3.95 | I4: 3.95 | J4: 3.95 | K4: 4.13 | L4: 4.42 | M4: 5.81 | N4: 20.43251
A5: BBVAGUB | B5: P | C5: Personas Físicas | D5: Fondos de Deuda | E5: Deuda Corto Plazo | F5: AAA/1 | G5: 1000000 | H5: 4.1 | I5: 4.1 | J5: 4.1 | K5: 4.28 | L5: 4.57 | M5: 5.95 | N5: 21.093226
A6: BBVAGUB | B6: PV | C6: Personas Físicas | D6: Fondos de Deuda | E6: Deuda Corto Plazo | F6: AAA/1 | G6: 20000000 | H6: 4.42 | I6: 4.43 | J6: 4.43 | K6: 4.61 | L6: 4.89 | M6: 6.27 | N6: 21.657065
A7: BBVAGUB | B7: UHN | C7: Personas Físicas | D7: Fondos de Deuda | E7: Deuda Corto Plazo | F7: AAA/1 | G7: 150000000 | H7: 5.27 | I7: 5.27 | J7: 5.27 | K7: 5.45 | L7: 5.72 | M7: 7.1 | N7: 24.967143
A8: BBVALIQ | B8: B | C8: Personas Físicas | D8: Fondos de Deuda | E8: Deuda Corto Plazo | F8: AAA/1 | G8: 0 | H8: 3.97 | I8: 4.08 | J8: 4.08 | K8: 4.28 | L8: 4.54 | M8: 5.89 | N8: 21.927829
A9: BBVALIQ | B9: C | C9: Personas Físicas | D9: Fondos de Deuda | E9: Deuda Corto Plazo | F9: AAA/1 | G9: 500000 | H9: 4.05 | I9: 4.16 | J9: 4.16 | K9: 4.35 | L9: 4.61 | M9: 5.97 | N9: 22.38631
A10: BBVALIQ | B10: P | C10: Personas Físicas | D10: Fondos de Deuda | E10: Deuda Corto Plazo | F10: AAA/1 | G10: 1000000 | H10: 4.19 | I10: 4.31 | J10: 4.31 | K10: 4.5 | L10: 4.76 | M10: 6.11 | N10: 23.09606
A11: BBVALIQ | B11: PV | C11: Personas Físicas | D11: Fondos de Deuda | E11: Deuda Corto Plazo | F11: AAA/1 | G11: 20000000 | H11: 4.53 | I11: 4.64 | J11: 4.64 | K11: 4.83 | L11: 5.09 | M11: 6.44 | N11: 24.024276
A12: BBVALIQ | B12: UHN | C12: Personas Físicas | D12: Fondos de Deuda | E12: Deuda Corto Plazo | F12: AAA/1 | G12: 150000000 | H12: 5.32 | I12: 5.43 | J12: 5.43 | K12: 5.62 | L12: 5.87 | M12: 7.22 | N12: 26.200838
A13: BBVAPYM | B13: PF1 | C13: Personas Físicas | D13: Fondos de Deuda | E13: Deuda Corto Plazo | F13: AAA/1 | G13: 0 | H13: 3.99 | I13: 3.96 | J13: 3.96 | K13: 4.11 | L13: 4.39 | M13: 5.78 | N13: 42.099883
... A80: BBVAPCD | B80: UHN2 | C80: Personas Físicas | D80: Fondos de Estrategias | E80: Fondos de Estrategias Dolarizados | F80: AA/7 | G80: 300000000 | H80: 0 | I80: 0 | J80: 0 | K80: 0 | L80: 0 | M80: 0 | N80: 0.006251
A81: BBVARV | B81: C | C81: Personas Físicas | D81: Fondos de Renta Variable | E81: Renta Variable Nacional | G81: 0 | H81: -1 | I81: 1.06 | J81: 1.06 | K81: 3.63 | L81: 12.09 | M81: 32.11 | N81: 16.805545
A82: BBVARV | B82: P | C82: Personas Físicas | D82: Fondos de Renta Variable | E82: Renta Variable Nacional | G82: 1000000 | H82: -0.99 | I82: 1.07 | J82: 1.07 | K82: 4.09 | L82: 12.74 | M82: 33.65 | N82: 18.363737
A83: BBVARV | B83: PV | C83: Personas Físicas | D83: Fondos de Renta Variable | E83: Renta Variable Nacional | G83: 20000000 | H83: -0.99 | I83: 1.08 | J83: 1.08 | K83: 4.56 | L83: 13.4 | M83: 35.25 | N83: 20.965501
A84: BBVARV | B84: UHN | C84: Personas Físicas | D84: Fondos de Renta Variable | E84: Renta Variable Nacional | G84: 150000000 | H84: -0.99 | I84: 1.09 | J84: 1.09 | K84: 5.02 | L84: 14.06 | M84: 36.83 | N84: 20.616307
A85: B+RVUS2 | B85: B | C85: Personas Físicas | D85: Fondos de Renta Variable | E85: Renta Variable Internacional | G85: 0 | H85: -0.31 | I85: 1.13 | J85: 1.13 | K85: 3.38 | L85: 0.82 | M85: 7.6 | N85: 122.12175
A86: B+RVUS2 | B86: C | C86: Personas Físicas | D86: Fondos de Renta Variable | E86: Renta Variable Internacional | G86: 500000 | H86: -0.31 | I86: 1.14 | J86: 1.14 | K86: 3.42 | L86: 0.88 | M86: 7.73 | N86: 129.09366
A87: B+RVUS2 | B87: P | C87: Personas Físicas | D87: Fondos de Renta Variable | E87: Renta Variable Internacional | G87: 1000000 | H87: -0.31 | I87: 1.15 | J87: 1.15 | K87: 3.88 | L87: 1.46 | M87: 8.98 | N87: 139.80408
A88: B+RVUS2 | B88: PV | C88: Personas Físicas | D88: Fondos de Renta Variable | E88: Renta Variable Internacional | G88: 20000000 | H88: -0.31 | I88: 1.16 | J88: 1.16 | K88: 4.34 | L88: 2.05 | M88: 10.28 | N88: 160.36059
A89: B+RVUS2 | B89: UHN | C89: Personas Físicas | D89: Fondos de Renta Variable | E89: Renta Variable Internacional | G89: 150000000 | H89: -0.31 | I89: 1.17 | J89: 1.17 | K89: 4.81 | L89: 2.65 | M89: 11.57 | N89: 159.38818
A90: B+RVUS2 | B90: UHN2 | C90: Personas Físicas | D90: Fondos de Renta Variable | E90: Renta Variable Internacional | G90: 300000000 | H90: -0.31 | I90: 1.17 | J90: 1.17 | K90: 5.04 | L90: 2.94 | M90: 12.21 | N90: 38.819418
A91: BBVACAP | B91: PV | C91: Personas Físicas | D91: Fondos de Renta Variable | E91: Renta Variable Internacional | G91: 100000 | H91: -0.51 | I91: -1.95 | J91: -1.95 | K91: -3.81 | L91: -5 | M91: -3.38 | N91: 14.621796
A92: BBVACRE | B92: C | C92: Personas Físicas | D92: Fondos de Renta Variable | E92: Renta Variable Internacional | G92: 500000 | H92: -0.01 | I92: 0.04 | J92: 0.04 | K92: 1.07 | L92: 2.86 | M92: 10.28 | N92: 100.56793
... A274: BBVAMA3 | B274: UHN2 | C274: Personas Físicas | D274: Fondos de MultiActivos | E274: Fondos de MultiActivos | G274: 300000000 | H274: -0.55 | I274: 0.34 | J274: 0.34 | K274: 0 | L274: 0 | M274: 0 | N274: 0.580559
A275: B+EDUCA | B275: E | C275: Personas Morales | D275: Fondos de Deuda | E275: Deuda Corto Plazo | F275: AAA/1 | G275: 5000 | H275: 5.75 | I275: 5.76 | J275: 5.76 | K275: 5.93 | L275: 6.2 | M275: 7.59 | N275: 0.270335
A276: BBVAGB2 | B276: E | C276: Personas Morales | D276: Fondos de Deuda | E276: Deuda Corto Plazo | F276: AAA/2 | G276: 0 | H276: 5.67 | I276: 6.76 | J276: 6.76 | K276: 5.26 | L276: 5.46 | M276: 6.86 | N276: 58.12014
A277: BBVAGB2 | B277: E1 | C277: Personas Morales | D277: Fondos de Deuda | E277: Deuda Corto Plazo | F277: AAA/2 | G277: 5000000 | H277: 6.08 | I277: 7.18 | J277: 7.18 | K277: 5.67 | L277: 5.87 | M277: 7.26 | N277: 61.464729
A278: BBVAGB2 | B278: E2 | C278: Personas Morales | D278: Fondos de Deuda | E278: Deuda Corto Plazo | F278: AAA/2 | G278: 50000000 | H278: 6.35 | I278: 7.44 | J278: 7.44 | K278: 5.92 | L278: 6.12 | M278: 7.52 | N278: 62.780703
A279: BBVAGBP | B279: E | C279: Personas Morales | D279: Fondos de Deuda | E279: Deuda Corto Plazo | F279: AAA/1 | G279: 0 | H279: 5.03 | I279: 5.02 | J279: 5.02 | K279: 5.22 | L279: 5.5 | M279: 6.86 | N279: 21.127215
A280: BBVAGBP | B280: E1 | C280: Personas Morales | D280: Fondos de Deuda | E280: Deuda Corto Plazo | F280: AAA/1 | G280: 150000000 | H280: 5.18 | I280: 5.16 | J280: 5.16 | K280: 5.37 | L280: 5.65 | M280: 7.02 | N280: 20.391307
A281: BBVAGOB | B281: E | C281: Personas Morales | D281: Fondos de Deuda | E281: Deuda Corto Plazo | F281: AAA/1 | G281: 0 | H281: 4.58 | I281: 4.66 | J281: 4.66 | K281: 4.83 | L281: 5.1 | M281: 6.48 | N281: 64.030049
A282: BBVAGOB | B282: E1 | C282: Personas Morales | D282: Fondos de Deuda | E282: Deuda Corto Plazo | F282: AAA/1 | G282: 15000000 | H282: 5.17 | I282: 5.25 | J282: 5.25 | K282: 5.41 | L282: 5.68 | M282: 7.04 | N282: 71.548941
A283: BBVAGOB | B283: E2 | C283: Personas Morales | D283: Fondos de Deuda | E283: Deuda Corto Plazo | F283: AAA/1 | G283: 100000000 | H283: 5.44 | I283: 5.53 | J283: 5.53 | K283: 5.68 | L283: 5.95 | M283: 7.31 | N283: 73.925764
A284: BBVAGOB | B284: TM | C284: Personas Morales | D284: Fondos de Deuda | E284: Deuda Corto Plazo | F284: AAA/1 | G284: 0 | H284: 5.84 | I284: 5.92 | J284: 5.92 | K284: 6.08 | L284: 6.35 | M284: 7.72 | N284: 72.987346
A285: BBVALIQ | B285: E | C285: Personas Morales | D285: Fondos de Deuda | E285: Deuda Corto Plazo | F285: AAA/1 | G285: 0 | H285: 5.28 | I285: 5.39 | J285: 5.39 | K285: 5.58 | L285: 5.84 | M285: 7.19 | N285: 24.877489
A286: BBVALIQ | B286: TM | C286: Personas Morales | D286: Fondos de Deuda | E286: Deuda Corto Plazo | F286: AAA/1 | G286: 0 | H286: 0 | I286: 0 | J286: 0 | K286: 0 | L286: 0 | M286: 0 | N286: 17.458099
... A341: BBVAPCD | B341: NC | C341: Personas Morales | D341: Fondos de Estrategias | E341: Fondos de Estrategias Dolarizados | F341: AA/7 | G341: 0 | H341: 0 | I341: 0 | J341: 0 | K341: 0 | L341: 0 | M341: 0 | N341: 0.00531
A342: BBVARV | B342: E | C342: Personas Morales | D342: Fondos de Renta Variable | E342: Renta Variable Nacional | G342: 0 | H342: -0.99 | I342: 1.08 | J342: 1.08 | K342: 4.82 | L342: 13.86 | M342: 36.49 | N342: 22.802894
A343: B+RVUS2 | B343: E | C343: Personas Morales | D343: Fondos de Renta Variable | E343: Renta Variable Internacional | G343: 0 | H343: -0.31 | I343: 1.16 | J343: 1.16 | K343: 4.41 | L343: 2.13 | M343: 10.46 | N343: 181.53249
A344: B+RVUS2 | B344: NC | C344: Personas Morales | D344: Fondos de Renta Variable | E344: Renta Variable Internacional | G344: 0 | H344: -0.31 | I344: 1.19 | J344: 1.19 | K344: 5.57 | L344: 3.62 | M344: 13.71 | N344: 198.63891
A345: BBVACAP | B345: E | C345: Personas Morales | D345: Fondos de Renta Variable | E345: Renta Variable Internacional | G345: 100000 | H345: -0.51 | I345: -1.95 | J345: -1.95 | K345: -3.81 | L345: -5 | M345: -3.38 | N345: 14.597888
A346: BBVACRE | B346: E | C346: Personas Morales | D346: Fondos de Renta Variable | E346: Renta Variable Internacional | G346: 0 | H346: -0.01 | I346: 0.04 | J346: 0.04 | K346: 1.12 | L346: 2.92 | M346: 10.4 | N346: 116.699
A347: BBVACRE | B347: NC | C347: Personas Morales | D347: Fondos de Renta Variable | E347: Renta Variable Internacional | G347: 0 | H347: -0.01 | I347: 0.07 | J347: 0.07 | K347: 2.25 | L347: 4.42 | M347: 13.66 | N347: 144.74255
A348: BBVACRE | B348: TM | C348: Personas Morales | D348: Fondos de Renta Variable | E348: Renta Variable Internacional | G348: 0 | H348: 0 | I348: 0 | J348: 0 | K348: 0 | L348: 0 | M348: 0 | N348: 25
A349: BBVACRE | B349: TNC | C349: Personas Morales | D349: Fondos de Renta Variable | E349: Renta Variable Internacional | G349: 0 | H349: 0 | I349: 0 | J349: 0 | K349: 0 | L349: 0 | M349: 0 | N349: 25
A350: BBVACRE | B350: GPF | C350: Personas Morales | D350: Fondos de Renta Variable | E350: Renta Variable Internacional | G350: 0 | H350: 0 | I350: 0 | J350: 0 | K350: 0 | L350: 0 | M350: 0 | N350: 25
A351: BBVADIG | B351: E | C351: Personas Morales | D351: Fondos de Renta Variable | E351: Renta Variable Internacional | G351: 0 | H351: -0.64 | I351: 1.87 | J351: 1.87 | K351: 19.36 | L351: 6.68 | M351: 0 | N351: 16.227687
A352: BBVADIG | B352: NC | C352: Personas Morales | D352: Fondos de Renta Variable | E352: Renta Variable Internacional | G352: 0 | H352: 0 | I352: 0 | J352: 0 | K352: 0 | L352: 0 | M352: 0 | N352: 9.919743
A353: BBVADIG | B353: TNC | C353: Personas Morales | D353: Fondos de Renta Variable | E353: Renta Variable Internacional | G353: 0 | H353: 0 | I353: 0 | J353: 0 | K353: 0 | L353: 0 | M353: 0 | N353: 10
... A428: BBVA66 | B428: NC3 | C428: Personas Morales | D428: Fondos de MultiActivos | E428: Fondos de MultiActivos | G428: 200000000 | H428: 0 | I428: 0 | J428: 0 | K428: 0 | L428: 0 | M428: 0 | N428: 10
A429: B+EDUCA | B429: GB | C429: Personas Morales | D429: Fondos de Deuda | E429: Deuda Corto Plazo | F429: AAA/1 | G429: 5000 | H429: 5.37 | I429: 5.39 | J429: 5.39 | K429: 0 | L429: 0 | M429: 0 | N429: 0.254629
A430: BBVAGUB | B430: GB | C430: Personas Morales | D430: Fondos de Deuda | E430: Deuda Corto Plazo | F430: AAA/1 | G430: 0 | H430: 5.44 | I430: 5.44 | J430: 5.44 | K430: 5.62 | L430: 5.9 | M430: 7.27 | N430: 24.667885
A431: BBVALIQ | B431: GB | C431: Personas Morales | D431: Fondos de Deuda | E431: Deuda Corto Plazo | F431: AAA/1 | G431: 0 | H431: 5.15 | I431: 5.26 | J431: 5.26 | K431: 5.45 | L431: 5.74 | M431: 7.14 | N431: 18.076819
A432: BBVARF | B432: GB | C432: Personas Morales | D432: Fondos de Deuda | E432: Deuda Corto Plazo | F432: AA/2 | G432: 0 | H432: 6 | I432: 6.26 | J432: 6.26 | K432: 5.67 | L432: 5.91 | M432: 7.21 | N432: 20.291681
A433: BBVADCB | B433: GB | C433: Personas Morales | D433: Fondos de Deuda | E433: Deuda Mediano Plazo | F433: AAA/2 | G433: 0 | H433: 5.85 | I433: 5.59 | J433: 5.59 | K433: 5.86 | L433: 6.07 | M433: 7.39 | N433: 14.34014
A434: BBVAPZO | B434: GB | C434: Personas Morales | D434: Fondos de Deuda | E434: Deuda Mediano Plazo | F434: AA/3 | G434: 0 | H434: 9.65 | I434: 30.73 | J434: 30.73 | K434: 8.1 | L434: 7.7 | M434: 9.87 | N434: 77.561769
A435: BBVACOR | B435: GB | C435: Personas Morales | D435: Fondos de Deuda | E435: Deuda Largo Plazo | F435: AA/4 | G435: 0 | H435: 29.64 | I435: 51.88 | J435: 51.88 | K435: 7.95 | L435: 7.43 | M435: 10.52 | N435: 26.015895
A436: BBVADLP | B436: GB | C436: Personas Morales | D436: Fondos de Deuda | E436: Deuda Largo Plazo | F436: AA/5 | G436: 0 | H436: 25.06 | I436: 49.88 | J436: 49.88 | K436: 7.35 | L436: 6.88 | M436: 10.04 | N436: 37.017216
A437: BBVADGA | B437: GB | C437: Personas Morales | D437: Fondos de Deuda | E437: Deuda Largo Plazo | F437: AAA/5 | G437: 0 | H437: 37.29 | I437: 48.26 | J437: 48.26 | K437: 5.21 | L437: 4.87 | M437: 8.21 | N437: 12.09245
A438: BBVAGLP | B438: GB | C438: Personas Morales | D438: Fondos de Deuda | E438: Deuda Largo Plazo | F438: AAA/5 | G438: 0 | H438: 228.72 | I438: 217.23 | J438: 217.23 | K438: 3.35 | L438: 3.69 | M438: 8.9 | N438: 25.43291
A439: BBVAUDI | B439: GB | C439: Personas Morales | D439: Fondos de Deuda | E439: Deuda Largo Plazo | F439: AAA/6 | G439: 0 | H439: 81.91 | I439: 77.01 | J439: 77.01 | K439: 6.62 | L439: 6.35 | M439: 9.1 | N439: 33.19276
A440: BBVAMRF | B440: GB | C440: Personas Morales | D440: Fondos de Deuda | E440: Retorno Absoluto | F440: AA/4 | G440: 0 | H440: 9.22 | I440: 5.25 | J440: 5.25 | K440: 6.62 | L440: 6.65 | M440: 8.33 | N440: 20.97213
... A445: BBVAPCD | B445: GB | C445: Personas Morales | D445: Fondos de Estrategias | E445: Fondos de Estrategias Dolarizados | F445: AA/7 | G445: 0 | H445: 0 | I445: 0 | J445: 0 | K445: 0 | L445: 0 | M445: 0 | N445: 0.005973
A446: BBVARV | B446: GB | C446: Personas Morales | D446: Fondos de Renta Variable | E446: Renta Variable Nacional | G446: 0 | H446: -0.99 | I446: 1.12 | J446: 1.12 | K446: 6.1 | L446: 15.59 | M446: 40.53 | N446: 29.009097
A447: BBVARFG | B447: GB | C447: Personas Morales | D447: Fondos de Renta Variable | E447: Renta Variable Nacional | G447: 0 | H447: -18.57 | I447: -21.28 | J447: -21.28 | K447: -0.09 | L447: -0.92 | M447: -1.15 | N447: 28.375694
A448: BBVARFL | B448: GB | C448: Personas Morales | D448: Fondos de Renta Variable | E448: Renta Variable Nacional | G448: 0 | H448: -0.42 | I448: -0.77 | J448: -0.77 | K448: -5.63 | L448: -6.87 | M448: -5.3 | N448: 24.282614
A449: B+RVUS2 | B449: GB | C449: Personas Morales | D449: Fondos de Renta Variable | E449: Renta Variable Internacional | G449: 0 | H449: -0.3 | I449: 1.19 | J449: 1.19 | K449: 5.88 | L449: 4.03 | M449: 14.59 | N449: 233.20851
A450: BBVACRE | B450: GB | C450: Personas Morales | D450: Fondos de Renta Variable | E450: Renta Variable Internacional | G450: 0 | H450: -0.01 | I450: 0.07 | J450: 0.07 | K450: 2.38 | L450: 4.6 | M450: 14.05 | N450: 148.62928
A451: BBVADIG | B451: GB | C451: Personas Morales | D451: Fondos de Renta Variable | E451: Renta Variable Internacional | G451: 0 | H451: -0.64 | I451: 1.89 | J451: 1.89 | K451: 20.28 | L451: 7.76 | M451: 53.92 | N451: 15.755009
A452: BBVARVE | B452: GB | C452: Personas Morales | D452: Fondos de Renta Variable | E452: Renta Variable Internacional | G452: 0 | H452: -1.19 | I452: -2.34 | J452: -2.34 | K452: 4.45 | L452: 6.44 | M452: 17.39 | N452: 3.631112
A453: BBVAEMG | B453: GB | C453: Personas Morales | D453: Fondos de Renta Variable | E453: Renta Variable Internacional | G453: 0 | H453: -1.23 | I453: 0.65 | J453: 0.65 | K453: 22.22 | L453: 22.81 | M453: 31.62 | N453: 19.100517
A454: BBVAESG | B454: GB | C454: Personas Morales | D454: Fondos de Renta Variable | E454: Renta Variable Internacional | G454: 0 | H454: -0.43 | I454: 1.1 | J454: 1.1 | K454: 9.13 | L454: 11.48 | M454: 28.66 | N454: 14.351303
A455: BBVANSH | B455: GB | C455: Personas Morales | D455: Fondos de Renta Variable | E455: Renta Variable Internacional | G455: 0 | H455: -0.91 | I455: 0.81 | J455: 0.81 | K455: 3.62 | L455: 10.87 | M455: 33.54 | N455: 174.41081
A456: BBVANDQ | B456: GB | C456: Personas Morales | D456: Fondos de Renta Variable | E456: Renta Variable Internacional | G456: 0 | H456: 0.17 | I456: 2.06 | J456: 2.06 | K456: 11.64 | L456: 12.83 | M456: 32.55 | N456: 202.57947
A457: BBVARFG | B457: GB | C457: Personas Morales | D457: Fondos de Renta Variable | E457: Renta Variable Internacional | G457: 0 | H457: -0.06 | I457: -0.46 | J457: -0.46 | K457: -0.07 | L457: -0.93 | M457: -2.31 | N457: 28.375694
... A485: BBVAMA3 | B485: GB | C485: Personas Morales | D485: Fondos de MultiActivos | E485: Fondos de MultiActivos | G485: 0 | H485: -0.55 | I485: 0.36 | J485: 0.36 | K485: 2.38 | L485: 3.63 | M485: 12.33 | N485: 0.642455

Sheet CLIENTES
A1: cliente_id | B1: nombre | C1: arquetipo | D1: perfil_riesgo | E1: posicion_mxn | F1: fondo_actual | G1: serie_actual | H1: categoria_actual | I1: rend_1_anio_actual | J1: clase_activo | K1: meses_sin_revision
A2: C001 | B2: Killer Croc | C2: Villano | D2: Moderado | E2: 11858000 | F2: BBVACR | G2: P | H2: Fondos de Estrategias Pesos | I2: 11.93 | J2: Deuda Corto Plazo | K2: 6
A3: C002 | B3: Wanda Maximoff | C3: Héroe | D3: Moderado | E3: 9732000 | F3: BBVAPZO | G3: C1 | H3: Deuda Mediano Plazo | I3: 5.92 | J3: Deuda Corto Plazo | K3: 1
A4: C003 | B4: Victor Fries | C4: Villano | D4: Conservador | E4: 13840000 | F4: BBVADCB | G4: P | H4: Deuda Mediano Plazo | I4: 4.63 | J4: Deuda Corto Plazo | K4: 6
A5: C004 | B5: Killmonger Stevens | C5: Villano | D5: Moderado | E5: 8829000 | F5: BBVAMA2 | G5: P | H5: Fondos de MultiActivos | I5: -1.78 | J5: Deuda Corto Plazo | K5: 0
A6: C005 | B6: Black Manta | C6: Villano | D6: Moderado | E6: 13805000 | F6: BBVALIQ | G6: P | H6: Deuda Corto Plazo | I6: 4.76 | J6: Deuda Corto Plazo | K6: 8
A7: C006 | B7: Emil Blonsky | C7: Villano | D7: Moderado | E7: 13226000 | F7: BBVAPZO | G7: B | H7: Deuda Mediano Plazo | I7: 5.86 | J7: Deuda Corto Plazo | K7: 8
A8: C007 | B8: Kara Danvers | C8: Héroe | D8: Agresivo | E8: 9479000 | F8: BBVAMA2 | G8: P | H8: Fondos de MultiActivos | I8: -1.78 | J8: Deuda Corto Plazo | K8: 0
A9: C008 | B9: Arthur Curry | C9: Héroe | D9: Moderado | E9: 19096000 | F9: BBVAMA3 | G9: P | H9: Fondos de MultiActivos | I9: 1.55 | J9: Deuda Corto Plazo | K9: 0
A10: C009 | B10: Solomon Grundy | C10: Villano | D10: Conservador | E10: 11177000 | F10: BBVAPZO | G10: B | H10: Deuda Mediano Plazo | I10: 5.86 | J10: Deuda Corto Plazo | K10: 5
A11: C010 | B11: Victor Stone | C11: Héroe | D11: Conservador | E11: 8645000 | F11: BBVALIQ | G11: B | H11: Deuda Corto Plazo | I11: 4.54 | J11: Deuda Corto Plazo | K11: 11
A12: C011 | B12: Mari McCabe | C12: Héroe | D12: Conservador | E12: 17665000 | F12: BBVADCB | G12: P | H12: Deuda Mediano Plazo | I12: 4.63 | J12: Deuda Corto Plazo | K12: 1
A13: C012 | B13: Susan Storm | C13: Héroe | D13: Agresivo | E13: 17334000 | F13: BBVADLP | G13: C | H13: Deuda Largo Plazo | I13: 4.28 | J13: Deuda Largo Plazo | K13: 8
... A151: C150 | B151: Sebastian Shaw | C151: Villano | D151: Agresivo | E151: 18445000 | F151: BBVAMA3 | G151: P | H151: Fondos de MultiActivos | I151: 1.55 | J151: Deuda Corto Plazo | K151: 1

Sheet DICCIONARIO
A1: Hoja | B1: Campo | C1: Tipo | D1: Descripción
A2: NOTAS_MERCADO | B2: id | C2: Texto | D2: Identificador único (N0001 a N0400)
A3: NOTAS_MERCADO | B3: fecha | C3: Fecha | D3: Publicación simulada, entre el 1 y el 8 de octubre de 2026
A4: NOTAS_MERCADO | B4: fuente | C4: Categórico | D4: Nota de análisis · Prensa financiera · Comunicado oficial · Resumen de mesa
A5: NOTAS_MERCADO | B5: clase_activo | C5: Categórico | D5: Deuda Corto Plazo · Deuda Largo Plazo · Renta Variable Nacional · Renta Variable Internacional · Divisas
A6: NOTAS_MERCADO | B6: texto | C6: Texto | D6: La nota de mercado. Longitud media de 25 palabras
A7: NOTAS_MERCADO | B7: impacto | C7: Categórico | D7: ETIQUETA OBJETIVO. POSITIVO · NEUTRAL · NEGATIVO. Efecto esperado sobre esa clase de activo
A8: NOTAS_MERCADO | B8: fenomeno | C8: Categórico | D8: directo · negacion · contraste · cifra_mixta · condicional
A9: NOTAS_MERCADO | B9: dificultad | C9: Categórico | D9: facil · media · dificil. Se deriva del fenómeno lingüístico
A10: NOTAS_MERCADO | B10: fondos_relacionados | C10: Texto | D10: Claves reales de fondos BBVA de esa clase de activo
A11: CATALOGO_FONDOS | B11: fondo | C11: Texto | D11: Clave del fondo (BBVAGUB, BBVARV, B+EDUCA…)
A12: CATALOGO_FONDOS | B12: serie | C12: Texto | D12: Serie accionaria (B, C, P, PV, UHN…)
... A28: CLIENTES | B28: meses_sin_revision | C28: Entero | D28: Meses desde la última revisión de portafolio

Sheet RESUMEN
A1: Distribución de la etiqueta objetivo (hoja NOTAS_MERCADO)
A2: Impacto | B2: Registros | C2: % del total
A3: POSITIVO | B3: =COUNTIF(NOTAS_MERCADO!$F$2:$F$401,A3) -> 158 | C3: =IFERROR(B3/$B$6,0) -> 0.395
A4: NEUTRAL | B4: =COUNTIF(NOTAS_MERCADO!$F$2:$F$401,A4) -> 84 | C4: =IFERROR(B4/$B$6,0) -> 0.21
A5: NEGATIVO | B5: =COUNTIF(NOTAS_MERCADO!$F$2:$F$401,A5) -> 158 | C5: =IFERROR(B5/$B$6,0) -> 0.395
A6: Total | B6: =SUM(B3:B5) -> 400 | C6: =IFERROR(B6/$B$6,0) -> 1
A8: Distribución por dificultad
A9: Dificultad | B9: Registros | C9: % del total
A10: facil | B10: =COUNTIF(NOTAS_MERCADO!$H$2:$H$401,A10) -> 195 | C10: =IFERROR(B10/$B$13,0) -> 0.4875
A11: media | B11: =COUNTIF(NOTAS_MERCADO!$H$2:$H$401,A11) -> 74 | C11: =IFERROR(B11/$B$13,0) -> 0.185
A12: dificil | B12: =COUNTIF(NOTAS_MERCADO!$H$2:$H$401,A12) -> 131 | C12: =IFERROR(B12/$B$13,0) -> 0.3275
A13: Total | B13: =SUM(B10:B12) -> 400 | C13: =IFERROR(B13/$B$13,0) -> 1
A15: Cartera simulada (hoja CLIENTES)
A16: Indicador | B16: Valor
A17: Clientes | B17: =COUNTA(CLIENTES!$A$2:$A$151) -> 150
A18: AUM simulado total | B18: =SUM(CLIENTES!$E$2:$E$151) -> 1831243000
A19: Posición promedio | B19: =IFERROR(B18/B17,0) -> 12208287
A20: Posición mínima | B20: =MIN(CLIENTES!$E$2:$E$151) -> 5186000
A21: Posición máxima | B21: =MAX(CLIENTES!$E$2:$E$151) -> 19690000
A23: Catálogo de fondos (hoja CATALOGO_FONDOS) — datos reales de BBVA al 08/10/2026
A24: Indicador | B24: Valor
A25: Series | B25: =COUNTA(CATALOGO_FONDOS!$A$2:$A$485) -> 484
A26: Series de Personas Físicas | B26: =COUNTIF(CATALOGO_FONDOS!$C$2:$C$485,"Personas Físicas") -> 273
A27: Rendimiento promedio a 1 año (%) | B27: =AVERAGE(CATALOGO_FONDOS!$L$2:$L$485) -> 3.8227479
